{
  "meta": {
    "id": "2025-08-23-burnley-sunderland",
    "kickoff_utc": "2025-08-23T14:00:00Z",
    "matchday": 2,
    "venue": null,
    "status": "finished",
    "home": {
      "slug": "burnley",
      "name": "Burnley",
      "primary": "#6C1D45",
      "crest": "https://crests.football-data.org/328.png"
    },
    "away": {
      "slug": "sunderland",
      "name": "Unknown",
      "primary": "#5A6470",
      "crest": "https://crests.football-data.org/71.png"
    },
    "score": {
      "home": 2,
      "away": 0
    }
  },
  "preview": null,
  "review": null
}