{
  "meta": {
    "id": "2025-12-03-liverpool-sunderland",
    "kickoff_utc": "2025-12-03T20:15:00Z",
    "matchday": 14,
    "venue": null,
    "status": "finished",
    "home": {
      "slug": "liverpool",
      "name": "Liverpool",
      "primary": "#C8102E",
      "crest": "https://crests.football-data.org/64.png"
    },
    "away": {
      "slug": "sunderland",
      "name": "Unknown",
      "primary": "#5A6470",
      "crest": "https://crests.football-data.org/71.png"
    },
    "score": {
      "home": 1,
      "away": 1
    }
  },
  "preview": null,
  "review": null
}