{
  "meta": {
    "id": "2026-01-07-crystal-palace-aston-villa",
    "kickoff_utc": "2026-01-07T19:30:00Z",
    "matchday": 21,
    "venue": null,
    "status": "finished",
    "home": {
      "slug": "crystal-palace",
      "name": "Crystal Palace",
      "primary": "#1B458F",
      "crest": "https://crests.football-data.org/354.png"
    },
    "away": {
      "slug": "aston-villa",
      "name": "Aston Villa",
      "primary": "#670E36",
      "crest": "https://crests.football-data.org/58.png"
    },
    "score": {
      "home": 0,
      "away": 0
    }
  },
  "preview": null,
  "review": null
}