{
  "meta": {
    "id": "2026-01-04-manchester-city-chelsea",
    "kickoff_utc": "2026-01-04T17:30:00Z",
    "matchday": 20,
    "venue": null,
    "status": "finished",
    "home": {
      "slug": "manchester-city",
      "name": "Manchester City",
      "primary": "#6CABDD",
      "crest": "https://prashan7h.github.io/football/assets/crests/manchester-city.png"
    },
    "away": {
      "slug": "chelsea",
      "name": "Chelsea",
      "primary": "#034694",
      "crest": "https://prashan7h.github.io/football/assets/crests/chelsea.png"
    },
    "score": {
      "home": 1,
      "away": 1
    }
  },
  "preview": null,
  "review": null
}