{
  "meta": {
    "id": "2026-04-11-liverpool-fulham",
    "kickoff_utc": "2026-04-11T16:30:00Z",
    "matchday": 32,
    "venue": null,
    "status": "finished",
    "home": {
      "slug": "liverpool",
      "name": "Liverpool",
      "primary": "#C8102E",
      "crest": "https://crests.football-data.org/64.png"
    },
    "away": {
      "slug": "fulham",
      "name": "Fulham",
      "primary": "#000000",
      "crest": "https://crests.football-data.org/63.png"
    },
    "score": {
      "home": 2,
      "away": 0
    }
  },
  "preview": null,
  "review": null
}